<?xml version="1.0" encoding="UTF-8"?>
<Nsrm>
  <!--The version of NsrmConfiguration file format-->
  <Version>1.0</Version>
  <!--Length of time in seconds to keep gate open each time it is opened
      valid values 1 to 24*60*60 seconds-->
  <GateOpenTime>30</GateOpenTime>
  <!--Time in seconds to wait before forcing gate open
      valid values 1 to 24*60*60 seconds-->
  <GateSyncTime>1200</GateSyncTime>
  <!--Mode to indicate how processes which share the same UID should be handled-->
  <SharedUIDMode>Conservative</SharedUIDMode>
  <!--List of applications which to apply Nsrm to-->
  <AppList Type="Exclusion">
  </AppList>
</Nsrm>
